signalwire_swaig/__init__.py
signalwire_swaig/response.py
signalwire_swaig/swaig.py
signalwire_swaig/swaig_cli.py
signalwire_swaig-2.7.2.dist-info/licenses/LICENSE
signalwire_swaig-2.7.2.dist-info/METADATA
signalwire_swaig-2.7.2.dist-info/WHEEL
signalwire_swaig-2.7.2.dist-info/entry_points.txt
signalwire_swaig-2.7.2.dist-info/top_level.txt
signalwire_swaig-2.7.2.dist-info/RECORD
