Metadata-Version: 2.4
Name: signalwire-swaig
Version: 2.7.2
Summary: A SignalWire SWAIG interface for AI Agents
Author-email: Brian West <brian@signalwire.com>
License-Expression: MIT
Project-URL: Homepage, https://github.com/briankwest/signalwire-swaig
Classifier: Programming Language :: Python :: 3
Classifier: Operating System :: OS Independent
Requires-Python: >=3.8
License-File: LICENSE
Requires-Dist: Flask
Requires-Dist: flask_httpauth
Dynamic: license-file
